lanun/__init__.py
lanun/cli.py
lanun/core/__init__.py
lanun/core/diagnostics.py
lanun/core/particles.py
lanun/core/solver.py
lanun/core/velocity.py
lanun/io/__init__.py
lanun/io/config_manager.py
lanun/io/data_handler.py
lanun/utils/__init__.py
lanun/utils/logger.py
lanun/utils/timer.py
lanun/visualization/__init__.py
lanun/visualization/animator.py
lanun-0.0.2.dist-info/LICENSE
lanun-0.0.2.dist-info/METADATA
lanun-0.0.2.dist-info/WHEEL
lanun-0.0.2.dist-info/entry_points.txt
lanun-0.0.2.dist-info/RECORD
