Metadata-Version: 2.3
Name: lanun
Version: 0.0.2
Summary: Numba-Accelerated 2D Lagrangian Transport for Idealized Ocean Basins
License: MIT
Keywords: lagrangian,transport,oceanography,particle-tracking,numba,geophysical-fluid-dynamics
Author: Sandy H. S. Herho
Author-email: sandy.herho@email.ucr.edu
Requires-Python: >=3.9,<4.0
Classifier: Development Status :: 3 - Alpha
Classifier: Intended Audience :: Science/Research
Classifier: License :: OSI Approved :: MIT License
Classifier: Operating System :: OS Independent
Classifier: Programming Language :: Python :: 3
Classifier: Programming Language :: Python :: 3.9
Classifier: Programming Language :: Python :: 3.10
Classifier: Programming Language :: Python :: 3.11
Classifier: Programming Language :: Python :: 3.12
Classifier: Programming Language :: Python :: 3.13
Classifier: Topic :: Scientific/Engineering :: Atmospheric Science
Classifier: Topic :: Scientific/Engineering :: Physics
Classifier: Topic :: Scientific/Engineering :: Visualization
Requires-Dist: Pillow (>=9.0.0)
Requires-Dist: matplotlib (>=3.5.0)
Requires-Dist: netCDF4 (>=1.5.0)
Requires-Dist: numba (>=0.56.0)
Requires-Dist: numpy (>=1.20.0)
Requires-Dist: pandas (>=1.3.0)
Requires-Dist: scipy (>=1.7.0)
Requires-Dist: tqdm (>=4.60.0)
Project-URL: Homepage, https://github.com/sandyherho/lanun
Project-URL: Repository, https://github.com/sandyherho/lanun
